.coveragerc
.gitignore
CHANGELOG.md
Dockerfile
LICENSE
MANIFEST.in
README.md
README_en.md
pyrightconfig.json
setup.py
.github/dependabot.yml
.github/workflows/codeql-analysis.yml
.github/workflows/smoketest.yml
docs/.nojekyll
docs/README.md
docs/_coverpage.md
docs/_sidebar.md
docs/index.html
docs/pages/0_what_is_it.md
docs/pages/1_where_can_it_be_used.md
docs/pages/2_how_to_use_it.md
docs/pages/3_how_it_works.md
docs/pages/4_roadmap.md
docs/pages/5_others.md
docs/pics/brand.svg
docs/pics/ssim_trend.png
docs/pics/stage.png
docs/pics/stagesepx.svg
stagesepx/__init__.py
stagesepx/api.py
stagesepx/cli.py
stagesepx/constants.py
stagesepx/hook.py
stagesepx/reporter.py
stagesepx/toolbox.py
stagesepx/video.py
stagesepx.egg-info/PKG-INFO
stagesepx.egg-info/SOURCES.txt
stagesepx.egg-info/dependency_links.txt
stagesepx.egg-info/entry_points.txt
stagesepx.egg-info/requires.txt
stagesepx.egg-info/top_level.txt
stagesepx/classifier/__init__.py
stagesepx/classifier/base.py
stagesepx/classifier/keras.py
stagesepx/classifier/ssim.py
stagesepx/classifier/svm.py
stagesepx/cutter/__init__.py
stagesepx/cutter/cut_range.py
stagesepx/cutter/cut_result.py
stagesepx/cutter/cutter.py
stagesepx/template/report.html